{
  "Musa Bin Nusair 407": {
    "lat": "24.7040468901298",
    "lng": "46.6818430779004",
    "source": "RPT"
  },
  "Musa Bin Nusair 306": {
    "lat": "24.7028717002021",
    "lng": "46.6793727108687",
    "source": "RPT"
  },
  "Musa Bin Nusair 308": {
    "lat": "24.7046671247878",
    "lng": "46.6838103883729",
    "source": "RPT"
  },
  "Musa Bin Nusair 309": {
    "lat": "24.7066747052637",
    "lng": "46.6883289142526",
    "source": "RPT"
  },
  "Al-Olaya 503": {
    "lat": "24.7064053975672",
    "lng": "46.6908891128127",
    "source": "RPT"
  },
  "Al-Olaya 504": {
    "lat": "24.7033695250668",
    "lng": "46.6915269166645",
    "source": "RPT"
  },
  "Al-Olaya 505": {
    "lat": "24.700970154125",
    "lng": "46.6922365857391",
    "source": "RPT"
  },
  "Al-Olaya 506": {
    "lat": "24.6970037457114",
    "lng": "46.6942488119758",
    "source": "RPT"
  },
  "Al-Olaya 507": {
    "lat": "24.6932249305266",
    "lng": "46.6955603522908",
    "source": "RPT"
  },
  "Al-Olaya 619": {
    "lat": "24.6921394181514",
    "lng": "46.6929642211193",
    "source": "RPT"
  },
  "Al-Olaya 618": {
    "lat": "24.6909559540359",
    "lng": "46.6901704605853",
    "source": "RPT"
  },
  "Al-Olaya 617": {
    "lat": "24.6901887368116",
    "lng": "46.6883468805583",
    "source": "RPT"
  },
  "Al-Olaya 517": {
    "lat": "24.6898051264283",
    "lng": "46.6879426386804",
    "source": "RPT"
  },
  "Al-Olaya 518": {
    "lat": "24.6907437454889",
    "lng": "46.6900896122097",
    "source": "RPT"
  },
  "Al-Olaya 519": {
    "lat": "24.6921067710162",
    "lng": "46.6933145640802",
    "source": "RPT"
  },
  "Al-Olaya 607": {
    "lat": "24.6940084523799",
    "lng": "46.6959645941687",
    "source": "RPT"
  },
  "Al-Olaya 606": {
    "lat": "24.6971751363398",
    "lng": "46.6943655929627",
    "source": "RPT"
  },
  "Al-Olaya 605": {
    "lat": "24.7012313123874",
    "lng": "46.6923623498789",
    "source": "RPT"
  },
  "Al-Olaya 604": {
    "lat": "24.7037041275463",
    "lng": "46.6917065797214",
    "source": "RPT"
  },
  "Al-Olaya 603": {
    "lat": "24.7071480325312",
    "lng": "46.6907723318258",
    "source": "RPT"
  },
  "As-Sulaimanyah 601": {
    "lat": "24.7086985747726",
    "lng": "46.68819416696",
    "source": "RPT"
  },
  "Al-Olaya 502": {
    "lat": "24.7067807960146",
    "lng": "46.6867299130467",
    "source": "RPT"
  },
  "Musa Bin Nusair 408": {
    "lat": "24.7053608046277",
    "lng": "46.6849332824782",
    "source": "RPT"
  }
}