{
  "Abi Jafar Al Mansoor 301": {
    "lat": "24.7871226320126",
    "lng": "46.731241435381",
    "source": "RPT"
  },
  "Abi Jafar Al Mansoor 302": {
    "lat": "24.7888271303583",
    "lng": "46.7352030057845",
    "source": "RPT"
  },
  "Abi Jafar Al Mansoor 304": {
    "lat": "24.7902787899101",
    "lng": "46.738652536476",
    "source": "RPT"
  },
  "Abi Jafar Al Mansoor 405": {
    "lat": "24.7915183958564",
    "lng": "46.7415810443026",
    "source": "RPT"
  },
  "Khalid Bin Al Walid 203": {
    "lat": "24.794013880783",
    "lng": "46.7435663210808",
    "source": "RPT"
  },
  "Khalid Bin Al Walid 202": {
    "lat": "24.7961831177385",
    "lng": "46.7424793595869",
    "source": "RPT"
  },
  "Khalid Bin Al Walid 201": {
    "lat": "24.7992330333421",
    "lng": "46.7409432404508",
    "source": "RPT"
  },
  "Saeed Bin Zaid 204": {
    "lat": "24.8042317969499",
    "lng": "46.7384459239606",
    "source": "RPT"
  },
  "Radwa 301": {
    "lat": "24.8053897199653",
    "lng": "46.7401886556121",
    "source": "RPT"
  },
  "Qurtubah 507": {
    "lat": "24.8059279058543",
    "lng": "46.7427937699364",
    "source": "RPT"
  },
  "Raya 301": {
    "lat": "24.805471263432",
    "lng": "46.7444287037537",
    "source": "RPT"
  },
  "Abdullah Bin Markhan 202": {
    "lat": "24.8074772158229",
    "lng": "46.7463421153091",
    "source": "RPT"
  },
  "Abdullah Bin Markhan 201": {
    "lat": "24.8106247017061",
    "lng": "46.744752097256",
    "source": "RPT"
  },
  "Al-Qalm 301": {
    "lat": "24.8125001086604",
    "lng": "46.7485340046027",
    "source": "RPT"
  },
  "Al-Qalm 302": {
    "lat": "24.8143102571519",
    "lng": "46.7528099853557",
    "source": "RPT"
  },
  "Al-Qalm 303": {
    "lat": "24.8160062281421",
    "lng": "46.7568074883706",
    "source": "RPT"
  },
  "Al-Qalm 304": {
    "lat": "24.8178978607076",
    "lng": "46.7612810984861",
    "source": "RPT"
  },
  "Rajia 101": {
    "lat": "24.8205966485525",
    "lng": "46.7638592633519",
    "source": "RPT"
  },
  "Mohammed Al Barqi 302": {
    "lat": "24.8223496061398",
    "lng": "46.7674255750304",
    "source": "RPT"
  },
  "Mohammed Al Barqi 303": {
    "lat": "24.8245020410603",
    "lng": "46.7725010563863",
    "source": "RPT"
  },
  "Mohammed Al Barqi 304": {
    "lat": "24.8257494578145",
    "lng": "46.7755193957414",
    "source": "RPT"
  },
  "Mohammed Al Barqi 305": {
    "lat": "24.8268174974702",
    "lng": "46.7780885774543",
    "source": "RPT"
  },
  "Mohammed Al Barqi 306": {
    "lat": "24.8278692221762",
    "lng": "46.7805409781803",
    "source": "RPT"
  },
  "Al Qiyas 201": {
    "lat": "24.8307553045529",
    "lng": "46.7804421634991",
    "source": "RPT"
  },
  "Al-Muanisiyah 506": {
    "lat": "24.82908399386",
    "lng": "46.7782143415941",
    "source": "RPT"
  },
  "Mohammed Al Barqi 405": {
    "lat": "24.8267115092137",
    "lng": "46.7769926328076",
    "source": "RPT"
  },
  "Mohammed Al Barqi 404": {
    "lat": "24.8258472938914",
    "lng": "46.7749804065708",
    "source": "RPT"
  },
  "Mohammed Al Barqi 403": {
    "lat": "24.8248037050872",
    "lng": "46.7724561406221",
    "source": "RPT"
  },
  "Mohammed Al Barqi 402": {
    "lat": "24.8225615900273",
    "lng": "46.7671470972922",
    "source": "RPT"
  },
  "Mohammed Al Barqi 401": {
    "lat": "24.8211510750296",
    "lng": "46.7638233307405",
    "source": "RPT"
  },
  "Al-Qalm 404": {
    "lat": "24.8182240013344",
    "lng": "46.7612721153333",
    "source": "RPT"
  },
  "Al-Qalm 403": {
    "lat": "24.8165525215471",
    "lng": "46.7573015617769",
    "source": "RPT"
  },
  "Al-Qalm 402": {
    "lat": "24.814872865486",
    "lng": "46.753304058762",
    "source": "RPT"
  },
  "Al-Qalm 401": {
    "lat": "24.8124919547786",
    "lng": "46.747662638777",
    "source": "RPT"
  },
  "Abdullah Bin Markhan 101": {
    "lat": "24.8093689785791",
    "lng": "46.7450575244527",
    "source": "RPT"
  },
  "Abdullah Bin Markhan 102": {
    "lat": "24.8073385941408",
    "lng": "46.7460456712653",
    "source": "RPT"
  },
  "Raya 401": {
    "lat": "24.8059686774173",
    "lng": "46.7450754907583",
    "source": "RPT"
  },
  "Radwa 402": {
    "lat": "24.806474243685",
    "lng": "46.742129016626",
    "source": "RPT"
  },
  "Radwa 401": {
    "lat": "24.8056669675332",
    "lng": "46.7404042512803",
    "source": "RPT"
  },
  "Saeed Bin Zaid 104": {
    "lat": "24.8035631322545",
    "lng": "46.7383291429737",
    "source": "RPT"
  },
  "Khalid Bin Al Walid 101": {
    "lat": "24.7986540444369",
    "lng": "46.7408264594639",
    "source": "RPT"
  },
  "Khalid Bin Al Walid 102": {
    "lat": "24.7958732290678",
    "lng": "46.7422278313073",
    "source": "RPT"
  },
  "Khalid Bin Al Walid 103": {
    "lat": "24.7932880749852",
    "lng": "46.7435214053166",
    "source": "RPT"
  },
  "Abi Jafar Al Mansoor 305": {
    "lat": "24.7913552905186",
    "lng": "46.7404401838916",
    "source": "RPT"
  },
  "Abi Jafar Al Mansoor 403": {
    "lat": "24.7896508269078",
    "lng": "46.7364157314182",
    "source": "RPT"
  },
  "Abi Jafar Al Mansoor 402": {
    "lat": "24.7883948913672",
    "lng": "46.7334243415217",
    "source": "RPT"
  },
  "Abi Jafar Al Mansoor 401": {
    "lat": "24.7867964095638",
    "lng": "46.7297142993978",
    "source": "RPT"
  }
}